<?xml version="1.0" encoding="UTF-8"?>
<metadata xmlns="http://www.demandware.com/xml/impex/metadata/2006-10-31">
    <type-extension type-id="SitePreferences">
        <custom-attribute-definitions>
            <attribute-definition attribute-id="siteLocale">
                <display-name xml:lang="x-default">Site Locale</display-name>
                <description xml:lang="x-default">US or EU</description>
                <type>string</type>
                <mandatory-flag>false</mandatory-flag>
                <externally-managed-flag>false</externally-managed-flag>
                <min-length>0</min-length>
                <default-value>US</default-value>
            </attribute-definition>
        </custom-attribute-definitions>
    </type-extension>
</metadata>
