<?xml version="1.0" encoding="UTF-8"?>
<site xmlns="http://www.demandware.com/xml/impex/site/2007-04-30" site-id="rapala">
    <name>Rapala</name>
    <currency>USD</currency>
    <taxation>net</taxation>
    <custom-cartridges>app_debugger:int_googletags:int_customfeeds:bm_paypal:int_paypal:app_cms:app_rapala_controllers:app_rapala_core:app_rapala_themes:app_rapala_vip:test_console:app_disbestpractice:bm_listrak:int_listrak_controllers:int_ups:app_rapala_insider_vip:int_browseratest:int_order_watcher:int_avatax</custom-cartridges>
    <storefront-status>online</storefront-status>
    <storefront-password>$s0$b0401$bxfQqHIlPJw6MtSO72BDOA==$6u2ySx3TrphyTNKPupnR31LBCmR7pFcw2ZpeEMjsgEE=</storefront-password>
</site>

